mathrix/__init__.py
mathrix-0.0.0.dist-info/LICENSE
mathrix-0.0.0.dist-info/METADATA
mathrix-0.0.0.dist-info/WHEEL
mathrix-0.0.0.dist-info/top_level.txt
mathrix-0.0.0.dist-info/RECORD
