Metadata-Version: 2.2
Name: mathrix
Version: 0.0.0
Summary: Coming soon (development in progress)
Author-email: Incircumscriptus <incircumscriptus.code@gmail.com>
Requires-Python: >=3.13
License-File: LICENSE
